cebeconf/XPS_spectra.py
cebeconf/__init__.py
cebeconf/cebe.py
cebeconf/cebe_kernels.py
cebeconf/cebe_params.py
cebeconf/cebe_representations.py
cebeconf/cebe_utils.py
cebeconf/data/C_model_delta_ACM.csv
cebeconf/data/C_model_delta_AtmEnv.csv
cebeconf/data/C_model_direct_ACM.csv
cebeconf/data/C_model_direct_AtmEnv.csv
cebeconf/data/C_representation_ACM.npy
cebeconf/data/C_representation_AtmEnv.npy
cebeconf/data/F_model_delta_ACM.csv
cebeconf/data/F_model_delta_AtmEnv.csv
cebeconf/data/F_model_direct_ACM.csv
cebeconf/data/F_model_direct_AtmEnv.csv
cebeconf/data/F_representation_ACM.npy
cebeconf/data/F_representation_AtmEnv.npy
cebeconf/data/N_model_delta_ACM.csv
cebeconf/data/N_model_delta_AtmEnv.csv
cebeconf/data/N_model_direct_ACM.csv
cebeconf/data/N_model_direct_AtmEnv.csv
cebeconf/data/N_representation_ACM.npy
cebeconf/data/N_representation_AtmEnv.npy
cebeconf/data/O_model_delta_ACM.csv
cebeconf/data/O_model_delta_AtmEnv.csv
cebeconf/data/O_model_direct_ACM.csv
cebeconf/data/O_model_direct_AtmEnv.csv
cebeconf/data/O_representation_ACM.npy
cebeconf/data/O_representation_AtmEnv.npy
cebeconf-1.0.2.dist-info/LICENSE
cebeconf-1.0.2.dist-info/METADATA
cebeconf-1.0.2.dist-info/WHEEL
cebeconf-1.0.2.dist-info/top_level.txt
cebeconf-1.0.2.dist-info/RECORD
